<?xml version="1.0"?>
<gconf>
	<entry name="cursor_shape" mtime="1414262410" type="string">
		<stringvalue>ibeam</stringvalue>
	</entry>
	<entry name="background_image" mtime="1367082086" type="string">
		<stringvalue>/home/luki/wall/phant.jpg</stringvalue>
	</entry>
	<entry name="backspace_binding" mtime="1357070655" type="string">
		<stringvalue>ascii-del</stringvalue>
	</entry>
	<entry name="delete_binding" mtime="1357070655" type="string">
		<stringvalue>escape-sequence</stringvalue>
	</entry>
	<entry name="login_shell" mtime="1357070392" type="bool" value="false"/>
	<entry name="font" mtime="1367082086" type="string">
		<stringvalue>DejaVu Sans Mono 10</stringvalue>
	</entry>
	<entry name="use_system_font" mtime="1367082086" type="bool" value="false"/>
	<entry name="background_darkness" mtime="1367082086" type="float" value="0"/>
	<entry name="background_type" mtime="1367082176" type="string">
		<stringvalue>solid</stringvalue>
	</entry>
	<entry name="use_theme_colors" mtime="1367082176" type="bool" value="false"/>
	<entry name="scrollback_lines" mtime="1367082086" type="int" value="1000"/>
	<entry name="scrollbar_position" mtime="1367082086" type="string">
		<stringvalue>hidden</stringvalue>
	</entry>
	<entry name="exit_action" mtime="1357070348" type="string">
		<stringvalue>close</stringvalue>
	</entry>
	<entry name="default_show_menubar" mtime="1367082086" type="bool" value="false"/>
	<entry name="palette" mtime="1367082436" type="string">
		<stringvalue>#1C1C1C1C1C1C:#BFFF3FFF3FFF:#9594E4E45454:#FFFFFFFF5757:#3E3E39396969:#737318186E6E:#20EAAADE8006:#D3D3D7D7CFCF:#555557575353:#E5E578786D6D:#CACAE9E98282:#EAEAE7E78888:#8888B8B8F6F6:#D7D78787FFFF:#757DEA20B57A:#EEEEEEEEECEC</stringvalue>
	</entry>
	<entry name="background_color" mtime="1367082440" type="string">
		<stringvalue>#1C1C1C1C1C1C</stringvalue>
	</entry>
	<entry name="visible_name" mtime="1367082086" type="string">
		<stringvalue>Default</stringvalue>
	</entry>
	<entry name="bold_color" mtime="1367082086" type="string">
		<stringvalue>#000000000000</stringvalue>
	</entry>
	<entry name="foreground_color" mtime="1367082086" type="string">
		<stringvalue>#D0D0D0D0D0D0</stringvalue>
	</entry>
</gconf>
